README.md
setup.py
litecache/__init__.py
litecache/cache.py
litecache.egg-info/PKG-INFO
litecache.egg-info/SOURCES.txt
litecache.egg-info/dependency_links.txt
litecache.egg-info/requires.txt
litecache.egg-info/top_level.txt