Metadata-Version: 1.1
Name: litecache
Version: 1.0.6
Summary: Thread safe query cache and async write for sqlite databases
Home-page: https://20ft.nz
Author: David Preece
Author-email: davep@20ft.nz
License: BSD
Keywords: sqlite sqlite3 asynchronous sql query cache inotify kqueue kevent
Platform: UNKNOWN
Classifier: Development Status :: 5 - Production/Stable
Classifier: Intended Audience :: Developers
Classifier: Intended Audience :: Information Technology
Classifier: License :: OSI Approved :: BSD License
Classifier: Topic :: Database
Classifier: Topic :: Software Development :: Libraries :: Python Modules
Classifier: Topic :: Utilities
Classifier: Programming Language :: Python :: 3.4
Classifier: Programming Language :: Python :: 3.5
Classifier: Programming Language :: Python :: 3.6
